daps/__init__.py
daps/createYAMLFromYacc.py
daps/generateDataFromYAML.py
daps/processStackOutput.py
daps-1.0.4.data/scripts/makeStates.sh
daps-1.0.4.dist-info/DESCRIPTION.rst
daps-1.0.4.dist-info/METADATA
daps-1.0.4.dist-info/RECORD
daps-1.0.4.dist-info/WHEEL
daps-1.0.4.dist-info/entry_points.txt
daps-1.0.4.dist-info/metadata.json
daps-1.0.4.dist-info/top_level.txt
